LICENCE
MANIFEST.in
README.md
pyproject.toml
setup.py
asyncdjangoorm/__init__.py
asyncdjangoorm/cli.py
asyncdjangoorm/main.py
asyncdjangoorm.egg-info/PKG-INFO
asyncdjangoorm.egg-info/SOURCES.txt
asyncdjangoorm.egg-info/dependency_links.txt
asyncdjangoorm.egg-info/entry_points.txt
asyncdjangoorm.egg-info/not-zip-safe
asyncdjangoorm.egg-info/requires.txt
asyncdjangoorm.egg-info/top_level.txt
asyncdjangoorm/_internal/__init__.py
asyncdjangoorm/_internal/manager.c
asyncdjangoorm/_internal/manager.py
asyncdjangoorm/_internal/queryset.c
asyncdjangoorm/_internal/queryset.py
asyncdjangoorm/config/__init__.py
asyncdjangoorm/config/base.py
asyncdjangoorm/config/init_tables.py
asyncdjangoorm/examples/__init__.py
asyncdjangoorm/examples/quick_start.py
asyncdjangoorm/migrations/__init__.py
asyncdjangoorm/migrations/ensure.py
asyncdjangoorm/migrations/env.py
asyncdjangoorm/migrations/manager.py
asyncdjangoorm/project_template/README.md
asyncdjangoorm/project_template/app.py
asyncdjangoorm/project_template/loader.py
asyncdjangoorm/project_template/manage.py
asyncdjangoorm/project_template/requirements.txt
asyncdjangoorm/project_template/settings.py
asyncdjangoorm/project_template/data/__init__.py
asyncdjangoorm/project_template/filters/__init__.py
asyncdjangoorm/project_template/handlers/__init__.py
asyncdjangoorm/project_template/handlers/channels/__init__.py
asyncdjangoorm/project_template/handlers/errors/__init__.py
asyncdjangoorm/project_template/handlers/errors/error_handler.py
asyncdjangoorm/project_template/handlers/groups/__init__.py
asyncdjangoorm/project_template/handlers/users/__init__.py
asyncdjangoorm/project_template/handlers/users/echo.py
asyncdjangoorm/project_template/handlers/users/help.py
asyncdjangoorm/project_template/handlers/users/start.py
asyncdjangoorm/project_template/keyboards/__init__.py
asyncdjangoorm/project_template/keyboards/default/__init__.py
asyncdjangoorm/project_template/keyboards/inline/__init__.py
asyncdjangoorm/project_template/middlewares/__init__.py
asyncdjangoorm/project_template/middlewares/throttling.py
asyncdjangoorm/project_template/states/__init__.py
asyncdjangoorm/project_template/utils/__init__.py
asyncdjangoorm/project_template/utils/notify_admins.py
