Metadata-Version: 2.4
Name: asyncdjangoorm
Version: 0.3.0
Summary: An asynchronous ORM inspired by Django's ORM, built on top of SQLAlchemy.
Author: Shohruhmirzo
Author-email: Shohruhmirzo <jamoliddinovshoh1@gmail.com>
License: MIT
Requires-Python: >=3.7
License-File: LICENCE
Requires-Dist: sqlalchemy>=2.0
Requires-Dist: alembic>=1.13
Requires-Dist: aiogram<4.0,>=2.25
Dynamic: author
Dynamic: license-file
Dynamic: requires-python
